variable_generators/__init__.py
variable_generators/generators.py
variable_generators-0.1.dist-info/LICENSE.txt
variable_generators-0.1.dist-info/METADATA
variable_generators-0.1.dist-info/WHEEL
variable_generators-0.1.dist-info/top_level.txt
variable_generators-0.1.dist-info/RECORD
